{
  "objects": [
    {
      "id": "cc05631e-0131-11ec-a459-600292b3fb79",
      "scene_object_name": "Table",
      "category": "Table",
      "3d_bbox": [
        [
          221,
          270,
          19.240550994873047
        ],
        [
          61,
          274,
          19.056840896606445
        ],
        [
          53,
          147,
          17.588624954223633
        ],
        [
          227,
          143,
          17.772335052490234
        ],
        [
          296,
          586,
          11.561458587646484
        ],
        [
          29,
          598,
          11.377748489379883
        ],
        [
          12,
          420,
          9.90953254699707
        ],
        [
          318,
          408,
          10.093241691589355
        ]
      ],
      "model_path": "data/models/Table/64b2121e41762bd47954eb05bbab463f/models/model_normalized.obj",
      "2d_bbox": [
        12,
        143,
        300,
        300
      ]
    },
    {
      "id": "cc05631f-0131-11ec-a459-600292b3fb79",
      "scene_object_name": "Bottle_inside_up_2021-08-19 23:09:52.995515",
      "category": "Bottle",
      "state": "upright",
      "3d_bbox": [
        [
          160,
          247,
          13.689064979553223
        ],
        [
          154,
          240,
          13.90446949005127
        ],
        [
          154,
          195,
          13.513379096984863
        ],
        [
          160,
          201,
          13.297974586486816
        ],
        [
          146,
          250,
          13.593111991882324
        ],
        [
          140,
          243,
          13.808515548706055
        ],
        [
          140,
          198,
          13.417425155639648
        ],
        [
          146,
          204,
          13.202020645141602
        ]
      ],
      "model_path": "data/models/Bottle/d8b6c270d29c58c55627157b31e16dc2/models/model_normalized.obj",
      "2d_bbox": [
        140,
        195,
        160,
        250
      ]
    },
    {
      "id": "cc056320-0131-11ec-a459-600292b3fb79",
      "scene_object_name": "Mug_inside_up_2021-08-19 23:09:53.005648",
      "category": "Mug_upside_down",
      "state": "upside_down",
      "3d_bbox": [
        [
          173,
          188,
          13.628804206848145
        ],
        [
          159,
          207,
          13.019731521606445
        ],
        [
          159,
          229,
          13.205427169799805
        ],
        [
          173,
          210,
          13.814499855041504
        ],
        [
          145,
          183,
          13.8065767288208
        ],
        [
          130,
          201,
          13.197504043579102
        ],
        [
          130,
          223,
          13.383199691772461
        ],
        [
          145,
          205,
          13.992271423339844
        ]
      ],
      "model_path": "data/models/Mug/df026976dc03197213ac44947b92716e/models/model_normalized.obj",
      "2d_bbox": [
        130,
        183,
        173,
        229
      ]
    }
  ],
  "relationships": [
    {
      "subject": "cc05631e-0131-11ec-a459-600292b3fb79",
      "object": "cc05631f-0131-11ec-a459-600292b3fb79",
      "predicate": "under"
    },
    {
      "subject": "cc05631f-0131-11ec-a459-600292b3fb79",
      "object": "cc05631e-0131-11ec-a459-600292b3fb79",
      "predicate": "on"
    },
    {
      "subject": "cc05631f-0131-11ec-a459-600292b3fb79",
      "object": "cc056320-0131-11ec-a459-600292b3fb79",
      "predicate": "inside"
    },
    {
      "subject": "cc056320-0131-11ec-a459-600292b3fb79",
      "object": "cc05631f-0131-11ec-a459-600292b3fb79",
      "predicate": "on"
    },
    {
      "subject": "cc05631f-0131-11ec-a459-600292b3fb79",
      "object": "cc056320-0131-11ec-a459-600292b3fb79",
      "predicate": "near"
    },
    {
      "subject": "cc056320-0131-11ec-a459-600292b3fb79",
      "object": "cc05631f-0131-11ec-a459-600292b3fb79",
      "predicate": "near"
    }
  ],
  "desired_relationships": [
    {
      "subject": "cc05631f-0131-11ec-a459-600292b3fb79",
      "object": "cc056320-0131-11ec-a459-600292b3fb79",
      "predicate": "inside_up"
    }
  ],
  "image_filename": "cc056321-0131-11ec-a459-600292b3fb79.png"
}