{
  "objects": [
    {
      "id": "f7a06975-0133-11ec-a459-600292b3fb79",
      "scene_object_name": "Table",
      "category": "Table",
      "3d_bbox": [
        [
          244,
          247,
          16.54118537902832
        ],
        [
          -6,
          283,
          15.892376899719238
        ],
        [
          -53,
          103,
          12.274123191833496
        ],
        [
          270,
          66,
          12.922931671142578
        ],
        [
          357,
          594,
          11.889732360839844
        ],
        [
          9,
          665,
          11.240923881530762
        ],
        [
          -57,
          556,
          7.622669696807861
        ],
        [
          447,
          463,
          8.271478652954102
        ]
      ],
      "model_path": "data/models/Table/82a60a0aaec8d532150d30262f9b49dc/models/model_normalized.obj",
      "2d_bbox": [
        0,
        66,
        300,
        300
      ]
    },
    {
      "id": "f7a06976-0133-11ec-a459-600292b3fb79",
      "scene_object_name": "Bottle_inside_up_2021-08-19 23:25:26.675268",
      "category": "Bottle",
      "state": "upright",
      "3d_bbox": [
        [
          159,
          238,
          10.38364315032959
        ],
        [
          138,
          240,
          10.358741760253906
        ],
        [
          138,
          196,
          9.700671195983887
        ],
        [
          160,
          194,
          9.72557258605957
        ],
        [
          162,
          255,
          10.189064025878906
        ],
        [
          141,
          257,
          10.164162635803223
        ],
        [
          140,
          213,
          9.506092071533203
        ],
        [
          163,
          211,
          9.530993461608887
        ]
      ],
      "model_path": "data/models/Bottle/957f897018c8c387b79156a61ad4c01/models/model_normalized.obj",
      "2d_bbox": [
        138,
        194,
        163,
        257
      ]
    },
    {
      "id": "f7a06977-0133-11ec-a459-600292b3fb79",
      "scene_object_name": "Mug_inside_up_2021-08-19 23:25:26.770924",
      "category": "Mug_upside_down",
      "state": "upside_down",
      "3d_bbox": [
        [
          166,
          174,
          9.892800331115723
        ],
        [
          172,
          214,
          9.42837905883789
        ],
        [
          171,
          242,
          9.827384948730469
        ],
        [
          165,
          202,
          10.2918062210083
        ],
        [
          128,
          177,
          9.859626770019531
        ],
        [
          132,
          217,
          9.3952054977417
        ],
        [
          133,
          245,
          9.794210433959961
        ],
        [
          128,
          205,
          10.25863265991211
        ]
      ],
      "model_path": "data/models/Mug/d7ba704184d424dfd56d9106430c3fe/models/model_normalized.obj",
      "2d_bbox": [
        128,
        174,
        172,
        245
      ]
    },
    {
      "id": "f7a06978-0133-11ec-a459-600292b3fb79",
      "scene_object_name": "Book_behind_2021-08-19 23:25:26.809637",
      "category": "Book",
      "state": "upright",
      "3d_bbox": [
        [
          166,
          156,
          11.452720642089844
        ],
        [
          170,
          129,
          11.861316680908203
        ],
        [
          170,
          123,
          11.768074989318848
        ],
        [
          167,
          150,
          11.359478950500488
        ],
        [
          121,
          153,
          11.505973815917969
        ],
        [
          126,
          126,
          11.914570808410645
        ],
        [
          126,
          119,
          11.821329116821289
        ],
        [
          120,
          147,
          11.412732124328613
        ]
      ],
      "model_path": "data/models/Book/g00d+b00k/untitled.obj",
      "2d_bbox": [
        120,
        119,
        170,
        156
      ]
    }
  ],
  "relationships": [
    {
      "subject": "f7a06975-0133-11ec-a459-600292b3fb79",
      "object": "f7a06976-0133-11ec-a459-600292b3fb79",
      "predicate": "under"
    },
    {
      "subject": "f7a06975-0133-11ec-a459-600292b3fb79",
      "object": "f7a06978-0133-11ec-a459-600292b3fb79",
      "predicate": "under"
    },
    {
      "subject": "f7a06976-0133-11ec-a459-600292b3fb79",
      "object": "f7a06975-0133-11ec-a459-600292b3fb79",
      "predicate": "on"
    },
    {
      "subject": "f7a06976-0133-11ec-a459-600292b3fb79",
      "object": "f7a06977-0133-11ec-a459-600292b3fb79",
      "predicate": "inside"
    },
    {
      "subject": "f7a06977-0133-11ec-a459-600292b3fb79",
      "object": "f7a06976-0133-11ec-a459-600292b3fb79",
      "predicate": "on"
    },
    {
      "subject": "f7a06976-0133-11ec-a459-600292b3fb79",
      "object": "f7a06977-0133-11ec-a459-600292b3fb79",
      "predicate": "near"
    },
    {
      "subject": "f7a06976-0133-11ec-a459-600292b3fb79",
      "object": "f7a06978-0133-11ec-a459-600292b3fb79",
      "predicate": "far"
    },
    {
      "subject": "f7a06976-0133-11ec-a459-600292b3fb79",
      "object": "f7a06978-0133-11ec-a459-600292b3fb79",
      "predicate": "in front of"
    },
    {
      "subject": "f7a06977-0133-11ec-a459-600292b3fb79",
      "object": "f7a06976-0133-11ec-a459-600292b3fb79",
      "predicate": "near"
    },
    {
      "subject": "f7a06977-0133-11ec-a459-600292b3fb79",
      "object": "f7a06978-0133-11ec-a459-600292b3fb79",
      "predicate": "far"
    },
    {
      "subject": "f7a06977-0133-11ec-a459-600292b3fb79",
      "object": "f7a06978-0133-11ec-a459-600292b3fb79",
      "predicate": "in front of"
    },
    {
      "subject": "f7a06978-0133-11ec-a459-600292b3fb79",
      "object": "f7a06975-0133-11ec-a459-600292b3fb79",
      "predicate": "on"
    },
    {
      "subject": "f7a06978-0133-11ec-a459-600292b3fb79",
      "object": "f7a06976-0133-11ec-a459-600292b3fb79",
      "predicate": "far"
    },
    {
      "subject": "f7a06978-0133-11ec-a459-600292b3fb79",
      "object": "f7a06976-0133-11ec-a459-600292b3fb79",
      "predicate": "behind"
    },
    {
      "subject": "f7a06978-0133-11ec-a459-600292b3fb79",
      "object": "f7a06977-0133-11ec-a459-600292b3fb79",
      "predicate": "far"
    },
    {
      "subject": "f7a06978-0133-11ec-a459-600292b3fb79",
      "object": "f7a06977-0133-11ec-a459-600292b3fb79",
      "predicate": "behind"
    }
  ],
  "desired_relationships": [
    {
      "subject": "f7a06976-0133-11ec-a459-600292b3fb79",
      "object": "f7a06977-0133-11ec-a459-600292b3fb79",
      "predicate": "inside_up"
    },
    {
      "object": "f7a06977-0133-11ec-a459-600292b3fb79",
      "subject": "f7a06978-0133-11ec-a459-600292b3fb79",
      "predicate": "behind"
    }
  ],
  "image_filename": "f7a06979-0133-11ec-a459-600292b3fb79.png"
}