{
  "objects": [
    {
      "id": "b1011b24-f551-11eb-a459-600292b3fb79",
      "scene_object_name": "Table",
      "category": "Table",
      "3d_bbox": [
        [
          208,
          278,
          25.35188865661621
        ],
        [
          83,
          280,
          25.222694396972656
        ],
        [
          80,
          166,
          23.974597930908203
        ],
        [
          211,
          165,
          24.10379409790039
        ],
        [
          246,
          447,
          17.56290626525879
        ],
        [
          66,
          452,
          17.433712005615234
        ],
        [
          59,
          296,
          16.18561553955078
        ],
        [
          253,
          293,
          16.31481170654297
        ]
      ],
      "model_path": "data/models/Table/1e6d470b0330afe7abccd5469c032787/models/model_normalized.obj",
      "2d_bbox": [
        59,
        165,
        253,
        300
      ]
    },
    {
      "id": "b1011b25-f551-11eb-a459-600292b3fb79",
      "scene_object_name": "Plate_on_2021-08-04 20:27:57.969301",
      "category": "Plate",
      "state": "upright",
      "3d_bbox": [
        [
          148,
          230,
          19.375852584838867
        ],
        [
          180,
          219,
          20.082489013671875
        ],
        [
          180,
          216,
          20.05646324157715
        ],
        [
          148,
          227,
          19.34982681274414
        ],
        [
          120,
          217,
          20.165746688842773
        ],
        [
          152,
          206,
          20.87238311767578
        ],
        [
          152,
          204,
          20.846357345581055
        ],
        [
          120,
          214,
          20.139720916748047
        ]
      ],
      "model_path": "data/models/Plate/plate6.blend",
      "2d_bbox": [
        120,
        204,
        180,
        230
      ]
    },
    {
      "id": "b1011b26-f551-11eb-a459-600292b3fb79",
      "scene_object_name": "Knife_on_2021-08-04 20:27:57.984873",
      "category": "Knife",
      "state": "upright",
      "3d_bbox": [
        [
          165,
          208,
          20.53008270263672
        ],
        [
          165,
          207,
          20.520221710205078
        ],
        [
          138,
          222,
          19.588741302490234
        ],
        [
          138,
          223,
          19.598602294921875
        ],
        [
          161,
          207,
          20.597579956054688
        ],
        [
          161,
          206,
          20.587718963623047
        ],
        [
          135,
          221,
          19.656238555908203
        ],
        [
          135,
          222,
          19.666099548339844
        ]
      ],
      "model_path": "data/models/Knife/knife2.blend",
      "2d_bbox": [
        135,
        206,
        165,
        223
      ]
    }
  ],
  "relationships": [
    {
      "subject": "b1011b24-f551-11eb-a459-600292b3fb79",
      "object": "b1011b25-f551-11eb-a459-600292b3fb79",
      "predicate": "under"
    },
    {
      "subject": "b1011b25-f551-11eb-a459-600292b3fb79",
      "object": "b1011b24-f551-11eb-a459-600292b3fb79",
      "predicate": "on"
    },
    {
      "subject": "b1011b25-f551-11eb-a459-600292b3fb79",
      "object": "b1011b26-f551-11eb-a459-600292b3fb79",
      "predicate": "under"
    },
    {
      "subject": "b1011b25-f551-11eb-a459-600292b3fb79",
      "object": "b1011b26-f551-11eb-a459-600292b3fb79",
      "predicate": "near"
    },
    {
      "subject": "b1011b26-f551-11eb-a459-600292b3fb79",
      "object": "b1011b25-f551-11eb-a459-600292b3fb79",
      "predicate": "on"
    },
    {
      "subject": "b1011b26-f551-11eb-a459-600292b3fb79",
      "object": "b1011b25-f551-11eb-a459-600292b3fb79",
      "predicate": "near"
    }
  ],
  "desired_relationships": [
    {
      "subject": "b1011b25-f551-11eb-a459-600292b3fb79",
      "object": "b1011b26-f551-11eb-a459-600292b3fb79",
      "predicate": "on"
    }
  ],
  "image_filename": "b1011b27-f551-11eb-a459-600292b3fb79.png"
}