{
  "objects": [
    {
      "id": "837e6826-eb1e-11eb-a252-600292b3fb79",
      "scene_object_name": "Table",
      "category": "Table",
      "3d_bbox": [
        [
          253,
          242,
          16.195396423339844
        ],
        [
          56,
          244,
          16.099807739257812
        ],
        [
          47,
          75,
          14.7809476852417
        ],
        [
          262,
          74,
          14.876535415649414
        ],
        [
          367,
          599,
          8.433415412902832
        ],
        [
          -13,
          607,
          8.3378267288208
        ],
        [
          -44,
          319,
          7.018965721130371
        ],
        [
          407,
          313,
          7.114553928375244
        ]
      ],
      "model_path": "data/models/Table/6d311facc6387a7fcd1233d74066ed8/models/model_normalized.obj",
      "2d_bbox": [
        0,
        74,
        300,
        300
      ]
    },
    {
      "id": "837e6827-eb1e-11eb-a252-600292b3fb79",
      "scene_object_name": "Book_left_behind_2021-07-22 20:56:25.288834",
      "category": "Book",
      "state": "upright",
      "3d_bbox": [
        [
          178,
          156,
          10.817215919494629
        ],
        [
          169,
          141,
          11.35969352722168
        ],
        [
          170,
          133,
          11.312982559204102
        ],
        [
          178,
          147,
          10.770505905151367
        ],
        [
          129,
          159,
          10.707026481628418
        ],
        [
          123,
          144,
          11.249503135681152
        ],
        [
          123,
          136,
          11.20279312133789
        ],
        [
          129,
          150,
          10.660316467285156
        ]
      ],
      "model_path": "data/models/Book/g00d+b00k/untitled.obj",
      "2d_bbox": [
        123,
        133,
        178,
        159
      ]
    },
    {
      "id": "837e6828-eb1e-11eb-a252-600292b3fb79",
      "scene_object_name": "Mug_left_behind_2021-07-22 20:56:25.302512",
      "category": "Mug",
      "state": "upright",
      "3d_bbox": [
        [
          28,
          123,
          12.16208553314209
        ],
        [
          63,
          130,
          11.830267906188965
        ],
        [
          62,
          99,
          11.648455619812012
        ],
        [
          26,
          92,
          11.98027229309082
        ],
        [
          47,
          114,
          12.56845760345459
        ],
        [
          82,
          121,
          12.236639976501465
        ],
        [
          81,
          90,
          12.054826736450195
        ],
        [
          46,
          84,
          12.38664436340332
        ]
      ],
      "model_path": "data/models/Mug/b6f30c63c946c286cf6897d8875cfd5e/models/model_normalized.obj",
      "2d_bbox": [
        26,
        84,
        82,
        130
      ]
    },
    {
      "id": "837e6829-eb1e-11eb-a252-600292b3fb79",
      "scene_object_name": "Mug_behind_2021-07-22 20:56:25.309809",
      "category": "Mug",
      "state": "upright",
      "3d_bbox": [
        [
          124,
          89,
          13.902843475341797
        ],
        [
          162,
          89,
          13.916069030761719
        ],
        [
          162,
          65,
          13.759875297546387
        ],
        [
          123,
          66,
          13.746649742126465
        ],
        [
          124,
          80,
          14.44172191619873
        ],
        [
          161,
          80,
          14.454948425292969
        ],
        [
          161,
          58,
          14.29875373840332
        ],
        [
          124,
          58,
          14.285528182983398
        ]
      ],
      "model_path": "data/models/Mug/a8f7a0edd3edc3299e54b4084dc33544/models/model_normalized.obj",
      "2d_bbox": [
        123,
        58,
        162,
        89
      ]
    }
  ],
  "relationships": [
    {
      "subject": "837e6826-eb1e-11eb-a252-600292b3fb79",
      "object": "837e6827-eb1e-11eb-a252-600292b3fb79",
      "predicate": "under"
    },
    {
      "subject": "837e6826-eb1e-11eb-a252-600292b3fb79",
      "object": "837e6828-eb1e-11eb-a252-600292b3fb79",
      "predicate": "under"
    },
    {
      "subject": "837e6826-eb1e-11eb-a252-600292b3fb79",
      "object": "837e6829-eb1e-11eb-a252-600292b3fb79",
      "predicate": "under"
    },
    {
      "subject": "837e6827-eb1e-11eb-a252-600292b3fb79",
      "object": "837e6826-eb1e-11eb-a252-600292b3fb79",
      "predicate": "on"
    },
    {
      "subject": "837e6827-eb1e-11eb-a252-600292b3fb79",
      "object": "837e6828-eb1e-11eb-a252-600292b3fb79",
      "predicate": "near"
    },
    {
      "subject": "837e6827-eb1e-11eb-a252-600292b3fb79",
      "object": "837e6828-eb1e-11eb-a252-600292b3fb79",
      "predicate": "right_front"
    },
    {
      "subject": "837e6827-eb1e-11eb-a252-600292b3fb79",
      "object": "837e6829-eb1e-11eb-a252-600292b3fb79",
      "predicate": "far"
    },
    {
      "subject": "837e6827-eb1e-11eb-a252-600292b3fb79",
      "object": "837e6829-eb1e-11eb-a252-600292b3fb79",
      "predicate": "in front of"
    },
    {
      "subject": "837e6828-eb1e-11eb-a252-600292b3fb79",
      "object": "837e6826-eb1e-11eb-a252-600292b3fb79",
      "predicate": "on"
    },
    {
      "subject": "837e6828-eb1e-11eb-a252-600292b3fb79",
      "object": "837e6827-eb1e-11eb-a252-600292b3fb79",
      "predicate": "near"
    },
    {
      "subject": "837e6828-eb1e-11eb-a252-600292b3fb79",
      "object": "837e6827-eb1e-11eb-a252-600292b3fb79",
      "predicate": "left_behind"
    },
    {
      "subject": "837e6828-eb1e-11eb-a252-600292b3fb79",
      "object": "837e6829-eb1e-11eb-a252-600292b3fb79",
      "predicate": "far"
    },
    {
      "subject": "837e6828-eb1e-11eb-a252-600292b3fb79",
      "object": "837e6829-eb1e-11eb-a252-600292b3fb79",
      "predicate": "left_front"
    },
    {
      "subject": "837e6829-eb1e-11eb-a252-600292b3fb79",
      "object": "837e6826-eb1e-11eb-a252-600292b3fb79",
      "predicate": "on"
    },
    {
      "subject": "837e6829-eb1e-11eb-a252-600292b3fb79",
      "object": "837e6827-eb1e-11eb-a252-600292b3fb79",
      "predicate": "far"
    },
    {
      "subject": "837e6829-eb1e-11eb-a252-600292b3fb79",
      "object": "837e6827-eb1e-11eb-a252-600292b3fb79",
      "predicate": "behind"
    },
    {
      "subject": "837e6829-eb1e-11eb-a252-600292b3fb79",
      "object": "837e6828-eb1e-11eb-a252-600292b3fb79",
      "predicate": "far"
    },
    {
      "subject": "837e6829-eb1e-11eb-a252-600292b3fb79",
      "object": "837e6828-eb1e-11eb-a252-600292b3fb79",
      "predicate": "right_behind"
    }
  ],
  "desired_relationships": [
    {
      "subject": "837e6827-eb1e-11eb-a252-600292b3fb79",
      "object": "837e6828-eb1e-11eb-a252-600292b3fb79",
      "predicate": "left_behind"
    },
    {
      "object": "837e6826-eb1e-11eb-a252-600292b3fb79",
      "subject": "837e6829-eb1e-11eb-a252-600292b3fb79",
      "predicate": "behind"
    }
  ],
  "image_filename": "837e682a-eb1e-11eb-a252-600292b3fb79.png"
}